[
    {
        "key": "dbln",
        "value": "%7B%2261574647416672%22%3A%22u4cBlYE7%22%7D",
        "domain": "facebook.com",
        "path": "/login/device-based/",
        "hostOnly": false,
        "creation": "2025-04-26T15:06:55.390Z",
        "lastAccessed": "2025-04-26T15:06:55.390Z"
    },
    {
        "key": "sb",
        "value": "zRMHaA2PupssFpHiKZAr0hAw",
        "domain": "facebook.com",
        "path": "/",
        "hostOnly": false,
        "creation": "2025-04-26T15:06:55.390Z",
        "lastAccessed": "2025-04-26T15:06:55.390Z"
    },
    {
        "key": "vpd",
        "value": "v1%3B687x375x2.8860480785369873",
        "domain": "facebook.com",
        "path": "/",
        "hostOnly": false,
        "creation": "2025-04-26T15:06:55.390Z",
        "lastAccessed": "2025-04-26T15:06:55.390Z"
    },
    {
        "key": "ps_l",
        "value": "1",
        "domain": "facebook.com",
        "path": "/",
        "hostOnly": false,
        "creation": "2025-04-26T15:06:55.390Z",
        "lastAccessed": "2025-04-26T15:06:55.390Z"
    },
    {
        "key": "ps_n",
        "value": "1",
        "domain": "facebook.com",
        "path": "/",
        "hostOnly": false,
        "creation": "2025-04-26T15:06:55.390Z",
        "lastAccessed": "2025-04-26T15:06:55.390Z"
    },
    {
        "key": "wl_cbv",
        "value": "v2%3Bclient_version%3A2791%3Btimestamp%3A1745340941",
        "domain": "facebook.com",
        "path": "/",
        "hostOnly": false,
        "creation": "2025-04-26T15:06:55.390Z",
        "lastAccessed": "2025-04-26T15:06:55.390Z"
    },
    {
        "key": "dpr",
        "value": "3.178847074508667",
        "domain": "facebook.com",
        "path": "/",
        "hostOnly": false,
        "creation": "2025-04-26T15:06:55.390Z",
        "lastAccessed": "2025-04-26T15:06:55.390Z"
    },
    {
        "key": "datr",
        "value": "KpAKaPPbaqpYFtX9FSFDHPD0",
        "domain": "facebook.com",
        "path": "/",
        "hostOnly": false,
        "creation": "2025-04-26T15:06:55.390Z",
        "lastAccessed": "2025-04-26T15:06:55.390Z"
    },
    {
        "key": "locale",
        "value": "en_US",
        "domain": "facebook.com",
        "path": "/",
        "hostOnly": false,
        "creation": "2025-04-26T15:06:55.390Z",
        "lastAccessed": "2025-04-26T15:06:55.390Z"
    },
    {
        "key": "wd",
        "value": "809x1484",
        "domain": "facebook.com",
        "path": "/",
        "hostOnly": false,
        "creation": "2025-04-26T15:06:55.390Z",
        "lastAccessed": "2025-04-26T15:06:55.390Z"
    },
    {
        "key": "c_user",
        "value": "100094261704542",
        "domain": "facebook.com",
        "path": "/",
        "hostOnly": false,
        "creation": "2025-04-26T15:06:55.390Z",
        "lastAccessed": "2025-04-26T15:06:55.390Z"
    },
    {
        "key": "xs",
        "value": "4%3AZWWvsWEwsS75ig%3A2%3A1745679999%3A-1%3A5903",
        "domain": "facebook.com",
        "path": "/",
        "hostOnly": false,
        "creation": "2025-04-26T15:06:55.390Z",
        "lastAccessed": "2025-04-26T15:06:55.390Z"
    },
    {
        "key": "fr",
        "value": "1bDF41lOS93KfOtUX.AWcL4J3lKusWGpQBh_55HOm_R3M89y0PbCewpD_qYDeVYoFg7m4.BoDNWT..AAA.0.0.BoDPaG.AWfkvLT2qQXQV1nQ8QgDft-lOQw",
        "domain": "facebook.com",
        "path": "/",
        "hostOnly": false,
        "creation": "2025-04-26T15:06:55.390Z",
        "lastAccessed": "2025-04-26T15:06:55.390Z"
    }
        ]
